cross_project_cluck/__init__.py
cross_project_cluck/cross_project_cluck.py
cross_project_cluck-1.0.6.dist-info/LICENSE
cross_project_cluck-1.0.6.dist-info/METADATA
cross_project_cluck-1.0.6.dist-info/WHEEL
cross_project_cluck-1.0.6.dist-info/entry_points.txt
cross_project_cluck-1.0.6.dist-info/top_level.txt
cross_project_cluck-1.0.6.dist-info/RECORD
