Metadata-Version: 2.1
Name: cross-project-cluck
Version: 1.0.6
Summary: CLI tool to identify cross project repo access in Azure DevOps.
Home-page: https://github.com/ytimyno/cross-project-cluck
Author: ytimyno
Author-email: ytimyno@gmail.com
License: GPLv3
Classifier: Programming Language :: Python :: 3
Classifier: License :: OSI Approved :: GNU General Public License v3 (GPLv3)
Classifier: Operating System :: OS Independent
License-File: LICENSE
